pynteract/__init__.py
pynteract/builtin_magics.py
pynteract/cli.py
pynteract/collector.py
pynteract/context.py
pynteract/future_utils.py
pynteract/magics.py
pynteract/namespace_utils.py
pynteract/ptk.py
pynteract/shell.py
pynteract/streams.py
pynteract/traceback_utils.py
pynteract/user_config.py
pynteract/utils.py
pynteract-0.1.1.dist-info/licenses/LICENSE
pynteract-0.1.1.dist-info/METADATA
pynteract-0.1.1.dist-info/WHEEL
pynteract-0.1.1.dist-info/entry_points.txt
pynteract-0.1.1.dist-info/top_level.txt
pynteract-0.1.1.dist-info/RECORD
