Metadata-Version: 2.4
Name: pynteract
Version: 0.1.1
Summary: Lightweight embedded, cell-oriented Python shell (notebooks/agents) with minimal dependencies.
License-Expression: MIT
Requires-Python: >=3.10
License-File: LICENSE
Requires-Dist: asttokens>=2.4
Provides-Extra: terminal
Requires-Dist: prompt-toolkit>=3.0; extra == "terminal"
Provides-Extra: dev
Requires-Dist: pytest>=7.0; extra == "dev"
Dynamic: license-file
